[
  {
    "run_id": "run_20251223_0134_6994",
    "timestamp": "2025-12-23T01:34:15.816724",
    "game_count": 74,
    "total_wealth": 6173403399,
    "top_prize_sum": 469203700,
    "birth_count": 0,
    "death_count": 0,
    "html_size_kb": 999.4052734375
  },
  {
    "run_id": "run_20251223_0154_c1bb",
    "timestamp": "2025-12-23T01:54:33.071074",
    "game_count": 74,
    "total_wealth": 6173403399,
    "top_prize_sum": 469203700,
    "birth_count": 0,
    "death_count": 0,
    "html_size_kb": 999.3935546875
  },
  {
    "run_id": "run_20251223_0234_5963",
    "timestamp": "2025-12-23T02:34:36.684398",
    "game_count": 74,
    "total_wealth": 6173403399,
    "top_prize_sum": 469203700,
    "birth_count": 0,
    "death_count": 0,
    "html_size_kb": 999.4033203125
  },
  {
    "run_id": "run_20251223_0356_a0e0",
    "timestamp": "2025-12-23T03:56:33.432390",
    "game_count": 74,
    "total_wealth": 6173403399,
    "top_prize_sum": 469203700,
    "birth_count": 0,
    "death_count": 0,
    "html_size_kb": 999.392578125
  },
  {
    "run_id": "run_20251223_0702_2fde",
    "timestamp": "2025-12-23T07:02:36.366844",
    "game_count": 74,
    "total_wealth": 6173403399,
    "top_prize_sum": 469203700,
    "birth_count": 0,
    "death_count": 0,
    "html_size_kb": 999.3994140625
  },
  {
    "run_id": "run_20251223_1350_d729",
    "timestamp": "2025-12-23T13:50:55.357788",
    "game_count": 74,
    "total_wealth": 6173403399,
    "top_prize_sum": 469203700,
    "birth_count": 0,
    "death_count": 0,
    "html_size_kb": 999.3779296875
  }
]